README.rst
setup.py
fling/__init__.py
fling/fling.py
fling.egg-info/PKG-INFO
fling.egg-info/SOURCES.txt
fling.egg-info/dependency_links.txt
fling.egg-info/entry_points.txt
fling.egg-info/requires.txt
fling.egg-info/top_level.txt