Metadata-Version: 1.1
Name: fling
Version: 0.1.1
Summary: Simple local file sharing over HTTP
Home-page: http://iffius.github.com
Author: Curtis Thompson
Author-email: curtis@oddpost.com
License: GPLv2
Platform: UNKNOWN
Classifier: Development Status :: 2 - Pre-Alpha
Classifier: Intended Audience :: Developers
Classifier: License :: OSI Approved :: GNU General Public License v2 (GPLv2)
Classifier: Natural Language :: English
Classifier: Programming Language :: Python
Classifier: Programming Language :: Python :: 2
Classifier: Programming Language :: Python :: 2.6
Classifier: Programming Language :: Python :: 2.7
Classifier: Topic :: Software Development :: Version Control
